{
  "openapi": "3.0.1",
  "info": {
    "title": "ApiExamples.ApiExamples",
    "version": "v1"
  },
  "paths": {
    "/api/Message": {
      "post": {
        "tags": [
          "Message"
        ],
        "requestBody": {
          "content": {
            "multipart/form-data": {
              "schema": {
                "type": "object",
                "properties": {
                  "Message": {
                    "type": "string"
                  },
                  "Email": {
                    "type": "string"
                  }
                }
              },
              "encoding": {
                "Message": {
                  "style": "form"
                },
                "Email": {
                  "style": "form"
                }
              }
            }
          }
        },
        "responses": {
          "200": {
            "description": "Success"
          }
        }
      }
    }
  },
  "components": { }
}